contenttype.py
contenttype-0.1.3.dist-info/LICENSE
contenttype-0.1.3.dist-info/METADATA
contenttype-0.1.3.dist-info/WHEEL
contenttype-0.1.3.dist-info/top_level.txt
contenttype-0.1.3.dist-info/RECORD
